AUTHORS
LICENSE
MANIFEST.in
README.rst
setup.py
akiokio_django_geoposition.egg-info/PKG-INFO
akiokio_django_geoposition.egg-info/SOURCES.txt
akiokio_django_geoposition.egg-info/dependency_links.txt
akiokio_django_geoposition.egg-info/not-zip-safe
akiokio_django_geoposition.egg-info/requires.txt
akiokio_django_geoposition.egg-info/top_level.txt
example/__init__.py
example/admin.py
example/models.py
example/tests.py
example/views.py
geoposition/__init__.py
geoposition/conf.py
geoposition/fields.py
geoposition/forms.py
geoposition/models.py
geoposition/widgets.py
geoposition/locale/ru/LC_MESSAGES/django.mo
geoposition/locale/ru/LC_MESSAGES/django.po
geoposition/static/geoposition/geoposition.css
geoposition/static/geoposition/geoposition.js
geoposition/templates/geoposition/widgets/geoposition.html
geoposition/tests/__init__.py
geoposition/tests/settings.py
geoposition/tests/test_geoposition.py
geoposition/tests/urls.py