Metadata-Version: 1.1
Name: akiokio-django-geoposition
Version: 0.2.2
Summary: Django model field that can hold a geoposition, and corresponding admin widget.
Home-page: http://github.com/akiokio/django-geoposition
Author: akiokio
Author-email: akio.xd@gmail.com
License: UNKNOWN
Download-URL: https://github.com/akiokio/django-geoposition/tarbal/0.2.2
Platform: UNKNOWN
Classifier: Development Status :: 4 - Beta
Classifier: Environment :: Web Environment
Classifier: Intended Audience :: Developers
Classifier: License :: OSI Approved :: BSD License
Classifier: Operating System :: OS Independent
Classifier: Programming Language :: Python
Classifier: Framework :: Django
